.gitignore
.travis.yml
LICENSE
README.md
pyproject.toml
setup.cfg
setup.py
tox.ini
stsci_aws_utils/__init__.py
stsci_aws_utils/s3.py
stsci_aws_utils.egg-info/PKG-INFO
stsci_aws_utils.egg-info/SOURCES.txt
stsci_aws_utils.egg-info/dependency_links.txt
stsci_aws_utils.egg-info/requires.txt
stsci_aws_utils.egg-info/top_level.txt
tests/__init__.py
tests/certificate.py
tests/conftest.py
tests/test_s3.py