Metadata-Version: 2.1
Name: stsci-aws-utils
Version: 0.1.2
Summary: Common AWS code for STScI applications
Home-page: https://github.com/spacetelescope/stsci-aws-utils
Author: STScI
Author-email: help@stsci.edu
License: BSD 3-Clause
Platform: UNKNOWN
Provides: stsci_aws_utils
Requires-Python: >=3.6
Provides-Extra: dev
